LICENSE
MANIFEST.in
README.rst
buildout.cfg
develop.cfg
pyproject.toml
requirements.txt
setup.py
version.txt
bob/__init__.py
bob.io.video.egg-info/PKG-INFO
bob.io.video.egg-info/SOURCES.txt
bob.io.video.egg-info/dependency_links.txt
bob.io.video.egg-info/entry_points.txt
bob.io.video.egg-info/not-zip-safe
bob.io.video.egg-info/requires.txt
bob.io.video.egg-info/top_level.txt
bob/io/__init__.py
bob/io/video/__init__.py
bob/io/video/bobskin.cpp
bob/io/video/bobskin.h
bob/io/video/file.cpp
bob/io/video/file.h
bob/io/video/main.cpp
bob/io/video/main.h
bob/io/video/reader.cpp
bob/io/video/test.py
bob/io/video/test_codec.py
bob/io/video/test_utils.py
bob/io/video/utils.py
bob/io/video/version.cpp
bob/io/video/writer.cpp
bob/io/video/cpp/reader.cpp
bob/io/video/cpp/reader.h
bob/io/video/cpp/utils.cpp
bob/io/video/cpp/utils.h
bob/io/video/cpp/writer.cpp
bob/io/video/cpp/writer.h
bob/io/video/data/test.mov
bob/io/video/data/test_h264.mov
bob/io/video/fonts/bold.ttf
bob/io/video/fonts/bold_italic.ttf
bob/io/video/fonts/font_license.txt
bob/io/video/fonts/italic.ttf
bob/io/video/fonts/regular.ttf
bob/io/video/script/__init__.py
bob/io/video/script/video_test.py
doc/conf.py
doc/guide.rst
doc/index.rst
doc/links.rst
doc/py_api.rst
doc/video.rst